homoglyphs-2.0.3.dist-info/dependency_links.txt
homoglyphs-2.0.3.dist-info/entry_points.txt
homoglyphs-2.0.3.dist-info/METADATA
homoglyphs-2.0.3.dist-info/top_level.txt
homoglyphs-2.0.3.dist-info/WHEEL
homoglyphs/core.py
homoglyphs/__init__.py
homoglyphs/confusables.json
homoglyphs/languages.json
homoglyphs/categories.json
homoglyphs-2.0.3.dist-info/LICENSE
homoglyphs-2.0.3.dist-info/RECORD