Metadata-Version: 2.1
Name: homoglyphs
Version: 2.0.3
Summary: Homoglyphs
Project-URL: Homepage, https://github.com/life4/homoglyphs
Author: orsinium
Author-email: master_fess@mail.ru
License: MIT
Requires-Python: >=3.5
Classifier: Development Status :: 5 - Production/Stable
Classifier: Intended Audience :: Developers
Classifier: License :: OSI Approved :: MIT License
Classifier: Programming Language :: Python :: 2
Classifier: Programming Language :: Python :: 2.7
Classifier: Programming Language :: Python :: 3.5
Classifier: Programming Language :: Python :: 3.6
Classifier: Programming Language :: Python :: 3.7
Classifier: Programming Language :: Python :: 3
Classifier: Programming Language :: Python
Classifier: Topic :: Software Development :: Libraries :: Python Modules
